{
    "pools": [
        {
            "entries": [
                {
                    "functions": [
                        {
                            "count": {
                                "max": 3,
                                "min": 1
                            },
                            "function": "set_count"
                        },
                        {
                            "data": 0,
                            "function": "set_data"
                        }
                    ],
                    "name": "minecraft:crying_obsidian",
                    "type": "item",
                    "weight": 1
                },
                {
                    "functions": [
                        {
                            "count": {
                                "max": 3,
                                "min": 1
                            },
                            "function": "set_count"
                        },
                        {
                            "data": 0,
                            "function": "set_data"
                        }
                    ],
                    "name": "minecraft:obsidian",
                    "type": "item",
                    "weight": 1
                },
                {
                    "functions": [
                        {
                            "count": {
                                "max": 1,
                                "min": 1
                            },
                            "function": "set_count"
                        },
                        {
                            "data": 15,
                            "function": "set_data"
                        }
                    ],
                    "name": "minecraft:shulker_box",
                    "type": "item",
                    "weight": 2
                },
                {
                    "functions": [
                        {
                            "count": {
                                "max": 1,
                                "min": 1
                            },
                            "function": "set_count"
                        },
                        {
                            "data": 0,
                            "function": "set_data"
                        }
                    ],
                    "name": "minecraft:mob_spawner",
                    "type": "item",
                    "weight": 1
                },
                {
                    "functions": [
                        {
                            "count": {
                                "max": 4,
                                "min": 1
                            },
                            "function": "set_count"
                        },
                        {
                            "data": 0,
                            "function": "set_data"
                        }
                    ],
                    "name": "tpkth:obsidian_nugget",
                    "type": "item",
                    "weight": 4
                },
                {
                    "functions": [
                        {
                            "count": {
                                "max": 3,
                                "min": 1
                            },
                            "function": "set_count"
                        },
                        {
                            "data": 0,
                            "function": "set_data"
                        }
                    ],
                    "name": "tpkth:obsidianChestChip",
                    "type": "item",
                    "weight": 1
                },
                {
                    "functions": [
                        {
                            "count": {
                                "max": 1,
                                "min": 1
                            },
                            "function": "set_count"
                        },
                        {
                            "data": 0,
                            "function": "set_data"
                        }
                    ],
                    "name": "minecraft:netherite_helmet",
                    "type": "item",
                    "weight": 1
                },
                {
                    "functions": [
                        {
                            "count": {
                                "max": 1,
                                "min": 1
                            },
                            "function": "set_count"
                        },
                        {
                            "data": 0,
                            "function": "set_data"
                        }
                    ],
                    "name": "minecraft:iron_boots",
                    "type": "item",
                    "weight": 1
                },
                {
                    "functions": [
                        {
                            "count": {
                                "max": 1,
                                "min": 1
                            },
                            "function": "set_count"
                        },
                        {
                            "data": 0,
                            "function": "set_data"
                        }
                    ],
                    "name": "minecraft:chainmail_chestplate",
                    "type": "item",
                    "weight": 1
                },
                {
                    "functions": [
                        {
                            "count": {
                                "max": 1,
                                "min": 1
                            },
                            "function": "set_count"
                        },
                        {
                            "data": 0,
                            "function": "set_data"
                        }
                    ],
                    "name": "minecraft:chainmail_leggings",
                    "type": "item",
                    "weight": 1
                },
                {
                    "functions": [
                        {
                            "count": {
                                "max": 1,
                                "min": 1
                            },
                            "function": "set_count"
                        },
                        {
                            "data": 0,
                            "function": "set_data"
                        }
                    ],
                    "name": "minecraft:chainmail_helmet",
                    "type": "item",
                    "weight": 1
                },
                {
                    "functions": [
                        {
                            "count": {
                                "max": 1,
                                "min": 1
                            },
                            "function": "set_count"
                        },
                        {
                            "data": 0,
                            "function": "set_data"
                        }
                    ],
                    "name": "minecraft:chainmail_boots",
                    "type": "item",
                    "weight": 1
                },
                {
                    "functions": [
                        {
                            "count": {
                                "max": 5,
                                "min": 1
                            },
                            "function": "set_count"
                        },
                        {
                            "data": 0,
                            "function": "set_data"
                        }
                    ],
                    "name": "minecraft:cooked_beef",
                    "type": "item",
                    "weight": 1
                },
                {
                    "functions": [
                        {
                            "count": {
                                "max": 1,
                                "min": 1
                            },
                            "function": "set_count"
                        },
                        {
                            "data": 0,
                            "function": "set_data"
                        }
                    ],
                    "name": "minecraft:crossbow",
                    "type": "item",
                    "weight": 1
                },
                {
                    "functions": [
                        {
                            "count": {
                                "max": 16,
                                "min": 1
                            },
                            "function": "set_count"
                        },
                        {
                            "data": 0,
                            "function": "set_data"
                        }
                    ],
                    "name": "minecraft:dried_kelp",
                    "type": "item",
                    "weight": 1
                },
                {
                    "functions": [
                        {
                            "count": {
                                "max": 8,
                                "min": 1
                            },
                            "function": "set_count"
                        },
                        {
                            "data": 0,
                            "function": "set_data"
                        }
                    ],
                    "name": "minecraft:chiseled_nether_bricks",
                    "type": "item",
                    "weight": 1
                },
                {
                    "functions": [
                        {
                            "count": {
                                "max": 7,
                                "min": 1
                            },
                            "function": "set_count"
                        },
                        {
                            "data": 0,
                            "function": "set_data"
                        }
                    ],
                    "name": "minecraft:cracked_nether_bricks",
                    "type": "item",
                    "weight": 3
                },
                {
                    "functions": [
                        {
                            "count": {
                                "max": 9,
                                "min": 1
                            },
                            "function": "set_count"
                        },
                        {
                            "data": 0,
                            "function": "set_data"
                        }
                    ],
                    "name": "minecraft:cobbled_deepslate",
                    "type": "item",
                    "weight": 4
                },
                {
                    "functions": [
                        {
                            "count": {
                                "max": 1,
                                "min": 1
                            },
                            "function": "set_count"
                        },
                        {
                            "data": 0,
                            "function": "set_data"
                        }
                    ],
                    "name": "minecraft:netherite_block",
                    "type": "item",
                    "weight": 1
                },
                {
                    "functions": [
                        {
                            "count": {
                                "max": 3,
                                "min": 1
                            },
                            "function": "set_count"
                        },
                        {
                            "data": 0,
                            "function": "set_data"
                        }
                    ],
                    "name": "minecraft:wither_skeleton_spawn_egg",
                    "type": "item",
                    "weight": 1
                },
                {
                    "functions": [
                        {
                            "count": {
                                "max": 1,
                                "min": 1
                            },
                            "function": "set_count"
                        },
                        {
                            "data": 0,
                            "function": "set_data"
                        }
                    ],
                    "name": "minecraft:netherite_ingot",
                    "type": "item",
                    "weight": 1
                },
                {
                    "functions": [
                        {
                            "count": {
                                "max": 3,
                                "min": 1
                            },
                            "function": "set_count"
                        },
                        {
                            "data": 0,
                            "function": "set_data"
                        }
                    ],
                    "name": "minecraft:netherite_scrap",
                    "type": "item",
                    "weight": 1
                },
                {
                    "functions": [
                        {
                            "count": {
                                "max": 7,
                                "min": 1
                            },
                            "function": "set_count"
                        },
                        {
                            "data": 0,
                            "function": "set_data"
                        }
                    ],
                    "name": "minecraft:nether_brick",
                    "type": "item",
                    "weight": 1
                },
                {
                    "functions": [
                        {
                            "count": {
                                "max": 8,
                                "min": 1
                            },
                            "function": "set_count"
                        },
                        {
                            "data": 0,
                            "function": "set_data"
                        }
                    ],
                    "name": "minecraft:nether_wart_block",
                    "type": "item",
                    "weight": 5
                },
                {
                    "functions": [
                        {
                            "count": {
                                "max": 1,
                                "min": 1
                            },
                            "function": "set_count"
                        },
                        {
                            "data": 0,
                            "function": "set_data"
                        }
                    ],
                    "name": "minecraft:soul_campfire",
                    "type": "item",
                    "weight": 1
                },
                {
                    "functions": [
                        {
                            "count": {
                                "max": 1,
                                "min": 1
                            },
                            "function": "set_count"
                        },
                        {
                            "data": 0,
                            "function": "set_data"
                        }
                    ],
                    "name": "minecraft:diamond_sword",
                    "type": "item",
                    "weight": 1
                },
                {
                    "functions": [
                        {
                            "count": {
                                "max": 8,
                                "min": 1
                            },
                            "function": "set_count"
                        },
                        {
                            "data": 0,
                            "function": "set_data"
                        }
                    ],
                    "name": "minecraft:quartz",
                    "type": "item",
                    "weight": 5
                },
                {
                    "functions": [
                        {
                            "count": {
                                "max": 6,
                                "min": 1
                            },
                            "function": "set_count"
                        },
                        {
                            "data": 0,
                            "function": "set_data"
                        }
                    ],
                    "name": "minecraft:netherbrick",
                    "type": "item",
                    "weight": 5
                },
                {
                    "functions": [
                        {
                            "count": {
                                "max": 1,
                                "min": 1
                            },
                            "function": "set_count"
                        },
                        {
                            "data": 1,
                            "function": "set_data"
                        }
                    ],
                    "name": "minecraft:skull",
                    "type": "item",
                    "weight": 1
                },
                {
                    "functions": [
                        {
                            "count": {
                                "max": 8,
                                "min": 1
                            },
                            "function": "set_count"
                        },
                        {
                            "data": 0,
                            "function": "set_data"
                        }
                    ],
                    "name": "minecraft:quartz_ore",
                    "type": "item",
                    "weight": 1
                },
                {
                    "functions": [
                        {
                            "count": {
                                "max": 8,
                                "min": 1
                            },
                            "function": "set_count"
                        },
                        {
                            "data": 0,
                            "function": "set_data"
                        }
                    ],
                    "name": "minecraft:nether_gold_ore",
                    "type": "item",
                    "weight": 1
                },
                {
                    "functions": [
                        {
                            "count": {
                                "max": 8,
                                "min": 1
                            },
                            "function": "set_count"
                        },
                        {
                            "data": 9,
                            "function": "set_data"
                        }
                    ],
                    "name": "minecraft:cobblestone_wall",
                    "type": "item",
                    "weight": 1
                },
                {
                    "functions": [
                        {
                            "count": {
                                "max": 8,
                                "min": 1
                            },
                            "function": "set_count"
                        },
                        {
                            "data": 13,
                            "function": "set_data"
                        }
                    ],
                    "name": "minecraft:cobblestone_wall",
                    "type": "item",
                    "weight": 1
                },
                {
                    "functions": [
                        {
                            "count": {
                                "max": 8,
                                "min": 1
                            },
                            "function": "set_count"
                        },
                        {
                            "data": 0,
                            "function": "set_data"
                        }
                    ],
                    "name": "minecraft:nether_brick_fence",
                    "type": "item",
                    "weight": 1
                },
                {
                    "functions": [
                        {
                            "count": {
                                "max": 2,
                                "min": 1
                            },
                            "function": "set_count"
                        },
                        {
                            "data": 0,
                            "function": "set_data"
                        }
                    ],
                    "name": "minecraft:enchanted_golden_apple",
                    "type": "item",
                    "weight": 1
                },
                {
                    "functions": [
                        {
                            "count": {
                                "max": 1,
                                "min": 1
                            },
                            "function": "set_count"
                        },
                        {
                            "data": 0,
                            "function": "set_data"
                        }
                    ],
                    "name": "minecraft:respawn_anchor",
                    "type": "item",
                    "weight": 1
                },
                {
                    "functions": [
                        {
                            "count": {
                                "max": 1,
                                "min": 1
                            },
                            "function": "set_count"
                        },
                        {
                            "data": 0,
                            "function": "set_data"
                        }
                    ],
                    "name": "minecraft:compass",
                    "type": "item",
                    "weight": 1
                },
                {
                    "functions": [
                        {
                            "count": {
                                "max": 1,
                                "min": 1
                            },
                            "function": "set_count"
                        },
                        {
                            "data": 0,
                            "function": "set_data"
                        }
                    ],
                    "name": "minecraft:beacon",
                    "type": "item",
                    "weight": 1
                }
            ],
            "rolls": 1
        },
        {
            "entries": [
                {
                    "functions": [
                        {
                            "count": {
                                "max": 8,
                                "min": 1
                            },
                            "function": "set_count"
                        },
                        {
                            "data": 0,
                            "function": "set_data"
                        }
                    ],
                    "name": "minecraft:glowstone",
                    "type": "item",
                    "weight": 8
                },
                {
                    "functions": [
                        {
                            "count": {
                                "max": 1,
                                "min": 1
                            },
                            "function": "set_count"
                        },
                        {
                            "data": 0,
                            "function": "set_data"
                        }
                    ],
                    "name": "minecraft:ender_chest",
                    "type": "item",
                    "weight": 1
                },
                {
                    "functions": [
                        {
                            "count": {
                                "max": 1,
                                "min": 1
                            },
                            "function": "set_count"
                        },
                        {
                            "data": 0,
                            "function": "set_data"
                        }
                    ],
                    "name": "minecraft:cauldron",
                    "type": "item",
                    "weight": 4
                },
                {
                    "functions": [
                        {
                            "count": {
                                "max": 1,
                                "min": 1
                            },
                            "function": "set_count"
                        },
                        {
                            "data": 0,
                            "function": "set_data"
                        }
                    ],
                    "name": "minecraft:enchanting_table",
                    "type": "item",
                    "weight": 1
                },
                {
                    "functions": [
                        {
                            "count": {
                                "max": 1,
                                "min": 1
                            },
                            "function": "set_count"
                        },
                        {
                            "data": 0,
                            "function": "set_data"
                        }
                    ],
                    "name": "minecraft:end_crystal",
                    "type": "item",
                    "weight": 1
                },
                {
                    "functions": [
                        {
                            "count": {
                                "max": 5,
                                "min": 1
                            },
                            "function": "set_count"
                        },
                        {
                            "data": 0,
                            "function": "set_data"
                        }
                    ],
                    "name": "minecraft:daylight_detector",
                    "type": "item",
                    "weight": 1
                },
                {
                    "functions": [
                        {
                            "count": {
                                "max": 1,
                                "min": 1
                            },
                            "function": "set_count"
                        },
                        {
                            "data": 0,
                            "function": "set_data"
                        }
                    ],
                    "name": "minecraft:shield",
                    "type": "item",
                    "weight": 1
                },
                {
                    "functions": [
                        {
                            "count": {
                                "max": 4,
                                "min": 1
                            },
                            "function": "set_count"
                        },
                        {
                            "data": 0,
                            "function": "set_data"
                        }
                    ],
                    "name": "minecraft:soul_lantern",
                    "type": "item",
                    "weight": 1
                },
                {
                    "functions": [
                        {
                            "count": {
                                "max": 3,
                                "min": 1
                            },
                            "function": "set_count"
                        },
                        {
                            "data": 0,
                            "function": "set_data"
                        }
                    ],
                    "name": "minecraft:hopper",
                    "type": "item",
                    "weight": 2
                },
                {
                    "functions": [
                        {
                            "count": {
                                "max": 1,
                                "min": 1
                            },
                            "function": "set_count"
                        },
                        {
                            "data": 0,
                            "function": "set_data"
                        }
                    ],
                    "name": "minecraft:ghast_tear",
                    "type": "item",
                    "weight": 1
                },
                {
                    "functions": [
                        {
                            "count": {
                                "max": 3,
                                "min": 1
                            },
                            "function": "set_count"
                        },
                        {
                            "data": 37,
                            "function": "set_data"
                        }
                    ],
                    "name": "minecraft:lingering_potion",
                    "type": "item",
                    "weight": 1
                },
                {
                    "functions": [
                        {
                            "count": {
                                "max": 3,
                                "min": 1
                            },
                            "function": "set_count"
                        },
                        {
                            "data": 5,
                            "function": "set_data"
                        }
                    ],
                    "name": "minecraft:lingering_potion",
                    "type": "item",
                    "weight": 3
                },
                {
                    "functions": [
                        {
                            "count": {
                                "max": 1,
                                "min": 1
                            },
                            "function": "set_count"
                        },
                        {
                            "data": 0,
                            "function": "set_data"
                        }
                    ],
                    "name": "minecraft:enchanted_book",
                    "type": "item",
                    "weight": 1
                }
            ],
            "rolls": 1
        }
    ]
}