{
  "particleeffect": {
    "direction": {
      "max": "0.0 0.0 0.0",
      "value": "Direction",
      "min": "0.0 0.0 0.0"
    },
    "emissionrate": {
      "max": "10.0",
      "min": "10.0"
    },
    "emittersize": {
      "value": "0.0 0.0 0.0"
    },
    "thickness": {
      "value": "0.0"
    },
    "relative": {
      "enable": "false"
    },
    "emittertype": {
      "value": "Sphere"
    },
    "texture": {
      "ani": {
        "name": "textures/sfxs/dy_load/canying",
        "fps": "60"
      },
      "name": "textures/sfxs/dy_load/canying"
    },
    "emitterscale": [],
    "velocity": {
      "max": "0.0",
      "min": "0.0"
    },
    "particlesize": {
      "max": "0.5 1.0",
      "min": "0.5 1.0"
    }
  }
}